ViPy/ViPy.py
ViPy/__init__.py
VegasInsiderPy-0.0.1.dist-info/LICENSE
VegasInsiderPy-0.0.1.dist-info/METADATA
VegasInsiderPy-0.0.1.dist-info/WHEEL
VegasInsiderPy-0.0.1.dist-info/top_level.txt
VegasInsiderPy-0.0.1.dist-info/RECORD
