Metadata-Version: 2.1
Name: VegasInsiderPy
Version: 0.0.1
Summary: Scraper for Vegas Insider historical odds and betting pages.
Home-page: https://github.com/bpewyllie/vipy
Author: Brady Wyllie
Author-email: bpewyllie@gmail.com
License: UNKNOWN
Platform: UNKNOWN
Classifier: Programming Language :: Python :: 3
Classifier: License :: OSI Approved :: MIT License
Classifier: Operating System :: OS Independent
Requires-Python: >=3.6
License-File: LICENSE
